{"created_at": "Wed Apr 18 07:29:38 +0000 2018", "id": 986507028842668032, "id_str": "986507028842668032", "text": "\"There is a great resistance in Afrin and this resistance is continuing.  Wherever our people are, they have to hel\u2026 https://t.co/dUuT63Kg54", "truncated": true, "entities": {"hashtags": [], "symbols": [], "user_mentions": [], "urls": [{"url": "https://t.co/dUuT63Kg54", "expanded_url": "https://twitter.com/i/web/status/986507028842668032", "display_url": "twitter.com/i/web/status/9\u2026", "indices": [117, 140]}]}, "metadata": {"iso_language_code": "en", "result_type": "recent"}, "source": "<a href=\"http://twitter.com\" rel=\"nofollow\">Twitter Web Client</a>", "in_reply_to_status_id": null, "in_reply_to_status_id_str": null, "in_reply_to_user_id": null, "in_reply_to_user_id_str": null, "in_reply_to_screen_name": null, "user": {"id": 703519972539174912, "id_str": "703519972539174912", "name": "Micha Grebsnig", "screen_name": "brulla_micha", "location": "Frankfurt / Montpellier", "description": "Internationalismus, Soziale Revolution, Autonomie, Human Rights", "url": null, "entities": {"description": {"urls": []}}, "protected": false, "followers_count": 658, "friends_count": 654, "listed_count": 49, "created_at": "Sat Feb 27 10:00:07 +0000 2016", "favourites_count": 1508, "utc_offset": -25200, "time_zone": "Pacific Time (US & Canada)", "geo_enabled": false, "verified": false, "statuses_count": 24960, "lang": "de", "contributors_enabled": false, "is_translator": false, "is_translation_enabled": false, "profile_background_color": "C0DEED", "profile_background_image_url": "http://pbs.twimg.com/profile_background_images/708309019916636160/bkA8qDRw.jpg", "profile_background_image_url_https": "https://pbs.twimg.com/profile_background_images/708309019916636160/bkA8qDRw.jpg", "profile_background_tile": false, "profile_image_url": "http://pbs.twimg.com/profile_images/703521021366771712/tR4IS7iS_normal.jpg", "profile_image_url_https": "https://pbs.twimg.com/profile_images/703521021366771712/tR4IS7iS_normal.jpg", "profile_banner_url": "https://pbs.twimg.com/profile_banners/703519972539174912/1459596898", "profile_link_color": "0084B4", "profile_sidebar_border_color": "000000", "profile_sidebar_fill_color": "000000", "profile_text_color": "000000", "profile_use_background_image": true, "has_extended_profile": false, "default_profile": false, "default_profile_image": false, "following": false, "follow_request_sent": false, "notifications": false, "translator_type": "none"}, "geo": null, "coordinates": null, "place": null, "contributors": null, "is_quote_status": true, "quoted_status_id": 986366949516070912, "quoted_status_id_str": "986366949516070912", "quoted_status": {"created_at": "Tue Apr 17 22:13:01 +0000 2018", "id": 986366949516070912, "id_str": "986366949516070912", "text": "TEV-DEM co-chair: A new phase has begun in Syria https://t.co/Z82lG8DlGC", "truncated": false, "entities": {"hashtags": [], "symbols": [], "user_mentions": [], "urls": [{"url": "https://t.co/Z82lG8DlGC", "expanded_url": "https://anfenglishmobile.com/features/tev-dem-co-chair-a-new-phase-has-begun-in-syria-26167", "display_url": "anfenglishmobile.com/features/tev-d\u2026", "indices": [49, 72]}]}, "metadata": {"iso_language_code": "en", "result_type": "recent"}, "source": "<a href=\"http://twitter.com\" rel=\"nofollow\">Twitter Web Client</a>", "in_reply_to_status_id": null, "in_reply_to_status_id_str": null, "in_reply_to_user_id": null, "in_reply_to_user_id_str": null, "in_reply_to_screen_name": null, "user": {"id": 282055947, "id_str": "282055947", "name": "Firat News Agency", "screen_name": "anfenglish", "location": "Amsterdam, The Netherlands", "description": "https://t.co/pkGlCqpnP8", "url": "https://t.co/FYvGHjFeXS", "entities": {"url": {"urls": [{"url": "https://t.co/FYvGHjFeXS", "expanded_url": "http://anfenglish.com", "display_url": "anfenglish.com", "indices": [0, 23]}]}, "description": {"urls": [{"url": "https://t.co/pkGlCqpnP8", "expanded_url": "http://anfenglishmobile.com", "display_url": "anfenglishmobile.com", "indices": [0, 23]}]}}, "protected": false, "followers_count": 23133, "friends_count": 6, "listed_count": 309, "created_at": "Thu Apr 14 13:24:49 +0000 2011", "favourites_count": 0, "utc_offset": 7200, "time_zone": "Amsterdam", "geo_enabled": false, "verified": false, "statuses_count": 23455, "lang": "en", "contributors_enabled": false, "is_translator": false, "is_translation_enabled": false, "profile_background_color": "000000", "profile_background_image_url": "http://abs.twimg.com/images/themes/theme1/bg.png", "profile_background_image_url_https": "https://abs.twimg.com/images/themes/theme1/bg.png", "profile_background_tile": false, "profile_image_url": "http://pbs.twimg.com/profile_images/848185707466280962/L-DGI6I-_normal.jpg", "profile_image_url_https": "https://pbs.twimg.com/profile_images/848185707466280962/L-DGI6I-_normal.jpg", "profile_banner_url": "https://pbs.twimg.com/profile_banners/282055947/1471964112", "profile_link_color": "3B94D9", "profile_sidebar_border_color": "000000", "profile_sidebar_fill_color": "000000", "profile_text_color": "000000", "profile_use_background_image": false, "has_extended_profile": false, "default_profile": false, "default_profile_image": false, "following": false, "follow_request_sent": false, "notifications": false, "translator_type": "none", "withheld_in_countries": ["TR"]}, "geo": null, "coordinates": null, "place": null, "contributors": null, "withheld_in_countries": ["TR"], "is_quote_status": false, "retweet_count": 12, "favorite_count": 16, "favorited": false, "retweeted": false, "possibly_sensitive": false, "lang": "en"}, "retweet_count": 1, "favorite_count": 1, "favorited": false, "retweeted": false, "possibly_sensitive": false, "lang": "en"}